{
    "title": "天干地支基础知识",
    "category": "tiangan_dizhi",
    "documents": [
        {
            "title": "天干概述",
            "content": "天干共有十个，依次为：甲、乙、丙、丁、戊、己、庚、辛、壬、癸。天干分阴阳：甲、丙、戊、庚、壬为阳干，乙、丁、己、辛、癸为阴干。天干配五行：甲乙属木，丙丁属火，戊己属土，庚辛属金，壬癸属水。"
        },
        {
            "title": "地支概述",
            "content": "地支共有十二个，依次为：子、丑、寅、卯、辰、巳、午、未、申、酉、戌、亥。地支分阴阳：子、寅、辰、午、申、戌为阳支，丑、卯、巳、未、酉、亥为阴支。地支配五行：寅卯属木，巳午属火，申酉属金，亥子属水，辰戌丑未属土。"
        },
        {
            "title": "六十甲子",
            "content": "天干与地支按顺序相配，形成六十种组合，称为六十甲子或六十花甲。从甲子开始，依次为甲子、乙丑、丙寅...直到癸亥，共六十组。六十甲子用于纪年、纪月、纪日、纪时，循环往复，周而复始。"
        },
        {
            "title": "地支藏干",
            "content": "每个地支中暗藏天干，称为藏干或人元：子藏癸，丑藏己癸辛，寅藏甲丙戊，卯藏乙，辰藏戊乙癸，巳藏丙戊庚，午藏丁己，未藏己丁乙，申藏庚壬戊，酉藏辛，戌藏戊辛丁，亥藏壬甲。藏干在八字分析中非常重要。"
        },
        {
            "title": "地支三合",
            "content": "地支三合是三个地支相合化成某一五行：申子辰三合水局，亥卯未三合木局，寅午戌三合火局，巳酉丑三合金局。三合是一种强大的合化力量，在八字和择日中应用广泛。"
        },
        {
            "title": "地支六合",
            "content": "地支六合是两个地支相合：子丑合土，寅亥合木，卯戌合火，辰酉合金，巳申合水，午未合土（或火土）。六合代表亲密和谐的关系，在八字婚配和人际关系分析中常用。"
        },
        {
            "title": "地支相冲",
            "content": "地支六冲是两个相隔六位的地支互相冲克：子午相冲，丑未相冲，寅申相冲，卯酉相冲，辰戌相冲，巳亥相冲。相冲代表对立、冲突、变动，在八字中遇冲多主变化不稳定。"
        },
        {
            "title": "地支相刑",
            "content": "地支相刑分三刑和自刑：寅巳申为无恩之刑，丑戌未为恃势之刑，子卯为无礼之刑，辰辰、午午、酉酉、亥亥为自刑。相刑多主刑伤、灾祸、不顺，在八字中需要特别注意。"
        },
        {
            "title": "地支相害",
            "content": "地支六害是两个地支互相损害：子未相害，丑午相害，寅巳相害，卯辰相害，申亥相害，酉戌相害。相害多主暗中受损、小人作祟、隐患暗病，程度轻于相冲。"
        },
        {
            "title": "十二长生",
            "content": "十二长生是天干在十二地支上的状态循环：长生、沐浴、冠带、临官、帝旺、衰、病、死、墓、绝、胎、养。每个天干从长生开始，按顺序（阳干顺行、阴干逆行）经历这十二种状态，用于判断天干的强弱。"
        }
    ]
}